[
  [
    [
      "How many cells does the organism start with initially?",
      "How often do the cells split and double in number?",
      "How many 3-day periods are there in 15 days?",
      "How many times do the cells double in number during the 15 days?",
      "What is the total number of cells at the end of each doubling period, especially the one at the end of the $15^\\text{th}$ day?"
    ],
    {
      "1": "How many cells does the organism start with initially?",
      "2": "How often do the cells split and double in number?",
      "3": "How many 3-day periods are there in 15 days?",
      "4": "How many times do the cells double in number during the 15 days?",
      "5": "What is the total number of cells at the end of each doubling period, especially the one at the end of the $15^\\text{th}$ day?"
    }
  ],
  [
    [
      "estion \"How many cells are there at the end of the 15th day?\", we need to follow these steps:",
      "Identify the starting number of cells.",
      "Determine the rate at which the cells split.",
      "Calculate how many times the cells split in the entire 15 day period.",
      "Determine how many cells result from each split.",
      "Calculate the total number of cells at the end of the 15th day."
    ],
    {
      "1": "estion \"How many cells are there at the end of the 15th day?\", we need to follow these steps:",
      "2": "Identify the starting number of cells.",
      "3": "Determine the rate at which the cells split.",
      "4": "Calculate how many times the cells split in the entire 15 day period.",
      "5": "Determine how many cells result from each split.",
      "6": "Calculate the total number of cells at the end of the 15th day."
    }
  ],
  [
    [
      "How often do the cells split?",
      "How many times do the cells split during the 15-day period?",
      "What is the total number of cells after each splitting event?",
      "Calculate the number of cells at the end of each three-day cycle.",
      "How many cells will there be at the end of the 15th day if this pattern continues?"
    ],
    {
      "1": "How often do the cells split?",
      "2": "How many times do the cells split during the 15-day period?",
      "3": "What is the total number of cells after each splitting event?",
      "4": "Calculate the number of cells at the end of each three-day cycle.",
      "5": "How many cells will there be at the end of the 15th day if this pattern continues?"
    }
  ],
  [
    [
      "How many times does cell division occur in 15 days given that division happens every 3 days?",
      "How many cells does one cell become after one division?",
      "How does the number of cells change with each division over the period of 15 days?"
    ],
    {
      "1": "How many times does cell division occur in 15 days given that division happens every 3 days?",
      "2": "How many cells does one cell become after one division?",
      "3": "How does the number of cells change with each division over the period of 15 days?"
    }
  ],
  [
    [
      "How many cells does the organism start with?",
      "How often do the cells divide?",
      "How many times do the cells divide in the total period of 15 days?",
      "What is the total number of cells after each division cycle?",
      "How do we calculate the total number of cells at the end of the 15th day using the information from the previous steps?"
    ],
    {
      "1": "How many cells does the organism start with?",
      "2": "How often do the cells divide?",
      "3": "How many times do the cells divide in the total period of 15 days?",
      "4": "What is the total number of cells after each division cycle?",
      "5": "How do we calculate the total number of cells at the end of the 15th day using the information from the previous steps?"
    }
  ],
  [
    [
      "How often do the cells split?",
      "How many times do the cells split within the 15-day period?",
      "How many cells does the organism start with?",
      "How many cells does each singular cell become after each split?",
      "What is the total number of cells after each split cycle?"
    ],
    {
      "1": "How often do the cells split?",
      "2": "How many times do the cells split within the 15-day period?",
      "3": "How many cells does the organism start with?",
      "4": "How many cells does each singular cell become after each split?",
      "5": "What is the total number of cells after each split cycle?"
    }
  ],
  [
    [
      "How often do the cells double in number?",
      "How many times do the cells double in 15 days?",
      "What is the initial number of cells?",
      "How can we calculate the total number of cells after each doubling?",
      "What is the total number of cells on the 15th day after repeated doublings?"
    ],
    {
      "1": "How often do the cells double in number?",
      "2": "How many times do the cells double in 15 days?",
      "3": "What is the initial number of cells?",
      "4": "How can we calculate the total number of cells after each doubling?",
      "5": "What is the total number of cells on the 15th day after repeated doublings?"
    }
  ],
  [
    [
      "How many times does the cell division occur in 15 days?",
      "What is the total number of cells after each division phase?",
      "What is the mathematical relationship or formula that represents the cell division over time?"
    ],
    {
      "1": "How many times does the cell division occur in 15 days?",
      "2": "What is the total number of cells after each division phase?",
      "3": "What is the mathematical relationship or formula that represents the cell division over time?"
    }
  ]
]