[
  [
    [
      "What does \"just before checking out\" imply regarding the setting of the shopping activity?",
      "Where are items typically placed just before the checkout process in a shopping context?",
      "Which of the options corresponds to a typical location for storing items selected for purchase right before paying?"
    ],
    {
      "1": "What does \"just before checking out\" imply regarding the setting of the shopping activity?",
      "2": "Where are items typically placed just before the checkout process in a shopping context?",
      "3": "Which of the options corresponds to a typical location for storing items selected for purchase right before paying?"
    },
    {
      "0": [
        "Step 1"
      ],
      "1": [
        "Step 2"
      ],
      "2": [
        "Step 3"
      ]
    },
    [
      [
        1,
        2
      ],
      [
        2,
        3
      ]
    ]
  ],
  [
    [
      "What does 'just before checking out' imply about the location within a store?\",",
      "In which container or area are items typically placed while shopping in a store, prior to making a purchase?\",",
      "Which of the provided options (mouth, grocery cart, supermarket, fruit basket, fruit market) correctly matches the typical purchasing process in a store?\"."
    ],
    {
      "1": "What does 'just before checking out' imply about the location within a store?\",",
      "2": "In which container or area are items typically placed while shopping in a store, prior to making a purchase?\",",
      "3": "Which of the provided options (mouth, grocery cart, supermarket, fruit basket, fruit market) correctly matches the typical purchasing process in a store?\"."
    },
    {
      "0": [
        "Step 1"
      ],
      "1": [
        "Step 2"
      ],
      "2": [
        "Step 3"
      ]
    },
    [
      [
        1,
        2
      ],
      [
        2,
        3
      ]
    ]
  ],
  [
    [
      "What is the typical process of shopping in a supermarket or grocery store?",
      "At which point in the shopping process are items usually placed in the grocery cart?",
      "What is the appropriate location for storing items such as grapes just before the checkout process?"
    ],
    {
      "1": "What is the typical process of shopping in a supermarket or grocery store?",
      "2": "At which point in the shopping process are items usually placed in the grocery cart?",
      "3": "What is the appropriate location for storing items such as grapes just before the checkout process?"
    },
    {
      "0": [
        "Step 1"
      ],
      "1": [
        "Step 2"
      ],
      "2": [
        "Step 3"
      ]
    },
    [
      [
        1,
        2
      ],
      [
        2,
        3
      ]
    ]
  ],
  [
    [
      "What process typically occurs just before checking out at a store?",
      "Where are items generally placed prior to the checkout process?",
      "Which of the provided options correctly corresponds to the place where an item is typically put just before the checkout?"
    ],
    {
      "1": "What process typically occurs just before checking out at a store?",
      "2": "Where are items generally placed prior to the checkout process?",
      "3": "Which of the provided options correctly corresponds to the place where an item is typically put just before the checkout?"
    },
    {
      "0": [
        "Step 1"
      ],
      "1": [
        "Step 2"
      ],
      "2": [
        "Step 3"
      ]
    },
    [
      [
        1,
        2
      ],
      [
        2,
        3
      ]
    ]
  ],
  [
    [
      "Where in a typical shopping scenario do people place items they intend to purchase?",
      "What do the terms \"checking out\" imply about the location within the store?",
      "Among the given options, which best represents where people would place items just before checking out?"
    ],
    {
      "1": "Where in a typical shopping scenario do people place items they intend to purchase?",
      "2": "What do the terms \"checking out\" imply about the location within the store?",
      "3": "Among the given options, which best represents where people would place items just before checking out?"
    },
    {
      "0": [
        "Step 1"
      ],
      "1": [
        "Step 2"
      ],
      "2": [
        "Step 3"
      ]
    },
    [
      [
        1,
        2
      ],
      [
        2,
        3
      ]
    ]
  ],
  [
    [
      "What does \"just before checking out\" signify about the location and action related to the grapes?",
      "Which locations listed are commonly near the checkout area in a typical grocery shopping scenario?",
      "From the options provided, where is it logical and appropriate to place an item intended for purchase right before checking out?"
    ],
    {
      "1": "What does \"just before checking out\" signify about the location and action related to the grapes?",
      "2": "Which locations listed are commonly near the checkout area in a typical grocery shopping scenario?",
      "3": "From the options provided, where is it logical and appropriate to place an item intended for purchase right before checking out?"
    },
    {
      "0": [
        "Step 1"
      ],
      "1": [
        "Step 2"
      ],
      "2": [
        "Step 3"
      ]
    },
    [
      [
        1,
        2
      ],
      [
        2,
        3
      ]
    ]
  ],
  [
    [
      "What actions typically occur with items you intend to purchase in a store just before checking out?",
      "Which of the options given represents a place where items are temporarily held during shopping before being purchased?",
      "Which option best aligns with standard shopping behavior in supermarkets or grocery stores?"
    ],
    {
      "1": "What actions typically occur with items you intend to purchase in a store just before checking out?",
      "2": "Which of the options given represents a place where items are temporarily held during shopping before being purchased?",
      "3": "Which option best aligns with standard shopping behavior in supermarkets or grocery stores?"
    },
    {
      "0": [
        "Step 1"
      ],
      "1": [
        "Step 2"
      ],
      "2": [
        "Step 3"
      ]
    },
    [
      [
        1,
        2
      ],
      [
        2,
        3
      ]
    ]
  ],
  [
    [
      "What is the scenario described in the question referring to?",
      "What are typical actions performed with groceries just before checking out at a supermarket?",
      "Which of the options represent a location within the supermarket where groceries are typically placed before checking out?"
    ],
    {
      "1": "What is the scenario described in the question referring to?",
      "2": "What are typical actions performed with groceries just before checking out at a supermarket?",
      "3": "Which of the options represent a location within the supermarket where groceries are typically placed before checking out?"
    },
    {
      "0": [
        "Step 1"
      ],
      "1": [
        "Step 2"
      ],
      "2": [
        "Step 3"
      ]
    },
    [
      [
        1,
        2
      ],
      [
        2,
        3
      ]
    ]
  ],
  [
    [
      "What is the context of \"just before checking out\"?",
      "Where do items typically get placed during the final stages before completing a purchase in a supermarket?",
      "Which of the given options (mouth, grocery cart, supermarket, fruit basket, fruit market) corresponds with the standard procedure or location for items that are about to be purchased?"
    ],
    {
      "1": "What is the context of \"just before checking out\"?",
      "2": "Where do items typically get placed during the final stages before completing a purchase in a supermarket?",
      "3": "Which of the given options (mouth, grocery cart, supermarket, fruit basket, fruit market) corresponds with the standard procedure or location for items that are about to be purchased?"
    },
    {
      "0": [
        "Step 1"
      ],
      "1": [
        "Step 2"
      ],
      "2": [
        "Step 3"
      ]
    },
    [
      [
        1,
        2
      ],
      [
        2,
        3
      ]
    ]
  ],
  [
    [
      "What is typically done with items intended for purchase in a grocery store setting just before checking out?",
      "Which of the options provided represent places where items can be physically placed just before they are purchased?",
      "From the valid options in question 2, which is the most practical and commonly used place for storing items just before checkout?"
    ],
    {
      "1": "What is typically done with items intended for purchase in a grocery store setting just before checking out?",
      "2": "Which of the options provided represent places where items can be physically placed just before they are purchased?",
      "3": "From the valid options in question 2, which is the most practical and commonly used place for storing items just before checkout?"
    },
    {
      "0": [
        "Step 1"
      ],
      "1": [
        "Step 2"
      ],
      "2": [
        "Step 3"
      ]
    },
    [
      [
        1,
        2
      ],
      [
        2,
        3
      ]
    ]
  ],
  [
    [
      "What does \"just before checking out\" imply about the location and the activity of the person?",
      "In which places can a person put grapes during the process of grocery shopping?",
      "Out of the identified options in question 2, which best corresponds to the typical action taken \"just before checking out\" in a grocery shopping context?"
    ],
    {
      "1": "What does \"just before checking out\" imply about the location and the activity of the person?",
      "2": "In which places can a person put grapes during the process of grocery shopping?",
      "3": "Out of the identified options in question 2, which best corresponds to the typical action taken \"just before checking out\" in a grocery shopping context?"
    },
    {
      "0": [
        "Step 1"
      ],
      "1": [
        "Step 2"
      ],
      "2": [
        "Step 3"
      ]
    },
    [
      [
        1,
        2
      ],
      [
        2,
        3
      ]
    ]
  ],
  [
    [
      "What does the phrase \"just before checking out\" imply about the location and activity being performed?",
      "In a typical grocery store setting, where are items placed when ready to be purchased?",
      "Which of the given options (mouth, grocery cart, supermarket, fruit basket, fruit market) is the most likely place you would place your grapes during this activity?"
    ],
    {
      "1": "What does the phrase \"just before checking out\" imply about the location and activity being performed?",
      "2": "In a typical grocery store setting, where are items placed when ready to be purchased?",
      "3": "Which of the given options (mouth, grocery cart, supermarket, fruit basket, fruit market) is the most likely place you would place your grapes during this activity?"
    },
    {
      "0": [
        "Step 1"
      ],
      "1": [
        "Step 2"
      ],
      "2": [
        "Step 3"
      ]
    },
    [
      [
        1,
        2
      ],
      [
        2,
        3
      ]
    ]
  ],
  [
    [
      "What does \"just before checking out\" imply about the action or activity?",
      "What are typical procedures when purchasing items in a grocery setting?",
      "Among the given options, which corresponds to the last step you take with an item before paying?"
    ],
    {
      "1": "What does \"just before checking out\" imply about the action or activity?",
      "2": "What are typical procedures when purchasing items in a grocery setting?",
      "3": "Among the given options, which corresponds to the last step you take with an item before paying?"
    },
    {
      "0": [
        "Step 1"
      ],
      "1": [
        "Step 2"
      ],
      "2": [
        "Step 3"
      ]
    },
    [
      [
        1,
        2
      ],
      [
        2,
        3
      ]
    ]
  ],
  [
    [
      "What is the context just before checking out in a grocery situation?",
      "Where are items typically placed prior to proceeding to the checkout counter?",
      "Out of the given options, which of them directly relates to the location for holding items that have been selected for purchase but not yet paid for?"
    ],
    {
      "1": "What is the context just before checking out in a grocery situation?",
      "2": "Where are items typically placed prior to proceeding to the checkout counter?",
      "3": "Out of the given options, which of them directly relates to the location for holding items that have been selected for purchase but not yet paid for?"
    },
    {
      "0": [
        "Step 1"
      ],
      "1": [
        "Step 2"
      ],
      "2": [
        "Step 3"
      ]
    },
    [
      [
        1,
        2
      ],
      [
        2,
        3
      ]
    ]
  ],
  [
    [
      "What actions are typically taken just before checking out at a store?",
      "Where would grapes logically be placed immediately before these actions occur?",
      "Among the options provided, which one corresponds to the usual practice of handling items before checkout in a grocery store setting?"
    ],
    {
      "1": "What actions are typically taken just before checking out at a store?",
      "2": "Where would grapes logically be placed immediately before these actions occur?",
      "3": "Among the options provided, which one corresponds to the usual practice of handling items before checkout in a grocery store setting?"
    },
    {
      "0": [
        "Step 1"
      ],
      "1": [
        "Step 2"
      ],
      "2": [
        "Step 3"
      ]
    },
    [
      [
        1,
        2
      ],
      [
        2,
        3
      ]
    ]
  ],
  [
    [
      "What does \"just before checking out\" imply about the location and context?",
      "What are the possible locations or containers for items in a supermarket setting?",
      "Among the options given (mouth, grocery cart, supermarket, fruit basket, fruit market), which one logically corresponds with the activity of preparing to check out?"
    ],
    {
      "1": "What does \"just before checking out\" imply about the location and context?",
      "2": "What are the possible locations or containers for items in a supermarket setting?",
      "3": "Among the options given (mouth, grocery cart, supermarket, fruit basket, fruit market), which one logically corresponds with the activity of preparing to check out?"
    },
    {
      "0": [
        "Step 1"
      ],
      "1": [
        "Step 2"
      ],
      "2": [
        "Step 3"
      ]
    },
    [
      [
        1,
        2
      ],
      [
        2,
        3
      ]
    ]
  ],
  [
    [
      "What is the context of \"just before checking out\" in relation to shopping?",
      "Where are items typically placed during the shopping process before they are paid for at the checkout?",
      "Which option corresponds to the logical location where one would store items to be scanned and purchased at the checkout in a grocery store environment?"
    ],
    {
      "1": "What is the context of \"just before checking out\" in relation to shopping?",
      "2": "Where are items typically placed during the shopping process before they are paid for at the checkout?",
      "3": "Which option corresponds to the logical location where one would store items to be scanned and purchased at the checkout in a grocery store environment?"
    },
    {
      "0": [
        "Step 1"
      ],
      "1": [
        "Step 2"
      ],
      "2": [
        "Step 3"
      ]
    },
    [
      [
        1,
        2
      ],
      [
        2,
        3
      ]
    ]
  ],
  [
    [
      "What does \"just before checking out\" imply about the location and activities during shopping?",
      "What are typical actions taken with items intended for purchase right before checking out in a store?",
      "Among the given options (mouth, grocery cart, supermarket, fruit basket, fruit market), which one logically represents where items would be placed immediately prior to checking out?"
    ],
    {
      "1": "What does \"just before checking out\" imply about the location and activities during shopping?",
      "2": "What are typical actions taken with items intended for purchase right before checking out in a store?",
      "3": "Among the given options (mouth, grocery cart, supermarket, fruit basket, fruit market), which one logically represents where items would be placed immediately prior to checking out?"
    },
    {
      "0": [
        "Step 1"
      ],
      "1": [
        "Step 2"
      ],
      "2": [
        "Step 3"
      ]
    },
    [
      [
        1,
        2
      ],
      [
        2,
        3
      ]
    ]
  ],
  [
    [
      "What does \"just before checking out\" imply about the location and activity?",
      "Where are grapes typically placed during the shopping process in a store?",
      "Which of the given options realistically represents a place where one puts an item just before paying for it?"
    ],
    {
      "1": "What does \"just before checking out\" imply about the location and activity?",
      "2": "Where are grapes typically placed during the shopping process in a store?",
      "3": "Which of the given options realistically represents a place where one puts an item just before paying for it?"
    },
    {
      "0": [
        "Step 1"
      ],
      "1": [
        "Step 2"
      ],
      "2": [
        "Step 3"
      ]
    },
    [
      [
        1,
        2
      ],
      [
        2,
        3
      ]
    ]
  ],
  [
    [
      "What does \"just before checking out\" imply about the location and actions taken in a grocery store?",
      "What are typical practices for handling items selected for purchase in a grocery store?",
      "Among the options provided (mouth, grocery cart, supermarket, fruit basket, fruit market), which location is directly associated with the process of finalizing purchases in a grocery store?"
    ],
    {
      "1": "What does \"just before checking out\" imply about the location and actions taken in a grocery store?",
      "2": "What are typical practices for handling items selected for purchase in a grocery store?",
      "3": "Among the options provided (mouth, grocery cart, supermarket, fruit basket, fruit market), which location is directly associated with the process of finalizing purchases in a grocery store?"
    },
    {
      "0": [
        "Step 1"
      ],
      "1": [
        "Step 2"
      ],
      "2": [
        "Step 3"
      ]
    },
    [
      [
        1,
        2
      ],
      [
        2,
        3
      ]
    ]
  ]
]