[
  [
    [
      "How many touchdowns did QB David Garrard throw?",
      "How many touchdowns did QB Jon Kitna throw?",
      "Compare the number of touchdowns thrown by David Garrard and Jon Kitna to determine who threw more."
    ],
    {
      "1": "How many touchdowns did QB David Garrard throw?",
      "2": "How many touchdowns did QB Jon Kitna throw?",
      "3": "Compare the number of touchdowns thrown by David Garrard and Jon Kitna to determine who threw more."
    }
  ],
  [
    [
      "How many touchdowns did QB David Garrard throw in the game?",
      "How many touchdowns did QB Jon Kitna throw in the game?",
      "Compare the number of touchdowns thrown by each quarterback to determine who threw more."
    ],
    {
      "1": "How many touchdowns did QB David Garrard throw in the game?",
      "2": "How many touchdowns did QB Jon Kitna throw in the game?",
      "3": "Compare the number of touchdowns thrown by each quarterback to determine who threw more."
    }
  ],
  [
    [
      "How many touchdowns did QB David Garrard throw during the entire game?",
      "How many touchdowns did QB Jon Kitna throw during the entire game?",
      "Compare the number of touchdowns thrown by David Garrard and Jon Kitna to determine which quarterback threw more."
    ],
    {
      "1": "How many touchdowns did QB David Garrard throw during the entire game?",
      "2": "How many touchdowns did QB Jon Kitna throw during the entire game?",
      "3": "Compare the number of touchdowns thrown by David Garrard and Jon Kitna to determine which quarterback threw more."
    }
  ],
  [
    [
      "How many touchdowns did David Garrard throw during the game?",
      "How many touchdowns did Jon Kitna throw during the game?",
      "Compare the number of touchdowns thrown by David Garrard and Jon Kitna to determine which quarterback threw more."
    ],
    {
      "1": "How many touchdowns did David Garrard throw during the game?",
      "2": "How many touchdowns did Jon Kitna throw during the game?",
      "3": "Compare the number of touchdowns thrown by David Garrard and Jon Kitna to determine which quarterback threw more."
    }
  ],
  [
    [
      "How many touchdowns did QB David Garrard throw in the game?",
      "How many touchdowns did QB Jon Kitna throw in the game?",
      "Compare the total touchdowns thrown by each quarterback to determine which one threw more."
    ],
    {
      "1": "How many touchdowns did QB David Garrard throw in the game?",
      "2": "How many touchdowns did QB Jon Kitna throw in the game?",
      "3": "Compare the total touchdowns thrown by each quarterback to determine which one threw more."
    }
  ],
  [
    [
      "How many touchdown passes did QB David Garrard complete?",
      "How many touchdown passes did QB Jon Kitna complete?",
      "Compare the number of touchdown passes completed by each quarterback to determine who threw more."
    ],
    {
      "1": "How many touchdown passes did QB David Garrard complete?",
      "2": "How many touchdown passes did QB Jon Kitna complete?",
      "3": "Compare the number of touchdown passes completed by each quarterback to determine who threw more."
    }
  ],
  [
    [
      "Identify all the touchdown passes made by QB David Garrard.",
      "Identify all the touchdown passes made by QB Jon Kitna.",
      "Compare the number of touchdown passes made by each quarterback to determine who threw more."
    ],
    {
      "1": "Identify all the touchdown passes made by QB David Garrard.",
      "2": "Identify all the touchdown passes made by QB Jon Kitna.",
      "3": "Compare the number of touchdown passes made by each quarterback to determine who threw more."
    }
  ],
  [
    [
      "How many touchdowns were thrown by QB David Garrard?",
      "How many touchdowns were thrown by QB Jon Kitna?",
      "Compare the counts from step 1 and step 2 to determine which quarterback threw more touchdowns."
    ],
    {
      "1": "How many touchdowns were thrown by QB David Garrard?",
      "2": "How many touchdowns were thrown by QB Jon Kitna?",
      "3": "Compare the counts from step 1 and step 2 to determine which quarterback threw more touchdowns."
    }
  ]
]