[
  [
    [
      "Identify all the touchdown (TD) passes mentioned in the text.",
      "Determine the yardage for each of these TD passes.",
      "Compare each TD pass’s yardage to see if it was over 10 yards.",
      "Add up the yardages of all the TD passes that were over 10 yards."
    ],
    {
      "1": "Identify all the touchdown (TD) passes mentioned in the text.",
      "2": "Determine the yardage for each of these TD passes.",
      "3": "Compare each TD pass’s yardage to see if it was over 10 yards.",
      "4": "Add up the yardages of all the TD passes that were over 10 yards."
    }
  ],
  [
    [
      "Identify all the touchdown (TD) passes mentioned in the passage.",
      "Determine the yardage for each TD pass.",
      "Filter out the TD passes where the yardage is 10 yards or less.",
      "Sum the yardage of the TD passes that are over 10 yards."
    ],
    {
      "1": "Identify all the touchdown (TD) passes mentioned in the passage.",
      "2": "Determine the yardage for each TD pass.",
      "3": "Filter out the TD passes where the yardage is 10 yards or less.",
      "4": "Sum the yardage of the TD passes that are over 10 yards."
    }
  ],
  [
    [
      "Identify which touchdown (TD) passes were over 10 yards based on the distances given.",
      "Sum the yardages of these specific TD passes to calculate the total yards for passes over 10 yards.",
      "Confirm the number of passes that were considered to ensure all relevant passes have been included in the total."
    ],
    {
      "1": "Identify which touchdown (TD) passes were over 10 yards based on the distances given.",
      "2": "Sum the yardages of these specific TD passes to calculate the total yards for passes over 10 yards.",
      "3": "Confirm the number of passes that were considered to ensure all relevant passes have been included in the total."
    }
  ],
  [
    [
      "Identify all the touchdown (TD) passes mentioned in the narrative.",
      "Determine the yardage of each identified TD pass.",
      "Filter out the TD passes that are 10 yards or less.",
      "Add up the yardage of the TD passes that are over 10 yards to find the total."
    ],
    {
      "1": "Identify all the touchdown (TD) passes mentioned in the narrative.",
      "2": "Determine the yardage of each identified TD pass.",
      "3": "Filter out the TD passes that are 10 yards or less.",
      "4": "Add up the yardage of the TD passes that are over 10 yards to find the total."
    }
  ],
  [
    [
      "Identify all the touchdown (TD) pass plays.",
      "Determine the yardage of each TD pass.",
      "Identify which TD passes were more than 10 yards.",
      "Sum the yardages of all TD passes that were over 10 yards."
    ],
    {
      "1": "Identify all the touchdown (TD) pass plays.",
      "2": "Determine the yardage of each TD pass.",
      "3": "Identify which TD passes were more than 10 yards.",
      "4": "Sum the yardages of all TD passes that were over 10 yards."
    }
  ],
  [
    [
      "Identify all the touchdown (TD) passes mentioned in the passage.",
      "Determine the yards covered for each TD pass.",
      "Filter out those TD passes that are 10 yards or less.",
      "Sum the yardage of the TD passes that are more than 10 yards."
    ],
    {
      "1": "Identify all the touchdown (TD) passes mentioned in the passage.",
      "2": "Determine the yards covered for each TD pass.",
      "3": "Filter out those TD passes that are 10 yards or less.",
      "4": "Sum the yardage of the TD passes that are more than 10 yards."
    }
  ],
  [
    [
      "Identify which touchdown (TD) passes were exactly 10 yards or less.",
      "List all the TD passes that were more than 10 yards.",
      "Calculate the total yards of these TD passes that were more than 10 yards."
    ],
    {
      "1": "Identify which touchdown (TD) passes were exactly 10 yards or less.",
      "2": "List all the TD passes that were more than 10 yards.",
      "3": "Calculate the total yards of these TD passes that were more than 10 yards."
    }
  ],
  [
    [
      "Identify all the touchdown (TD) passes mentioned in the passage.",
      "Determine the yardage of each TD pass.",
      "Verify which of these TD passes were made from over 10 yards.",
      "Sum the yardages of only those TD passes that were greater than 10 yards."
    ],
    {
      "1": "Identify all the touchdown (TD) passes mentioned in the passage.",
      "2": "Determine the yardage of each TD pass.",
      "3": "Verify which of these TD passes were made from over 10 yards.",
      "4": "Sum the yardages of only those TD passes that were greater than 10 yards."
    }
  ]
]